web_health_checker/__init__.py
web_health_checker/__main__.py
web_health_checker/contrib/__init__.py
web_health_checker/contrib/fastapi.py
web_health_checker/contrib/flask.py
web_health_checker/contrib/quart.py
web_health_checker-1.3.1.dist-info/LICENSE
web_health_checker-1.3.1.dist-info/METADATA
web_health_checker-1.3.1.dist-info/WHEEL
web_health_checker-1.3.1.dist-info/top_level.txt
web_health_checker-1.3.1.dist-info/RECORD
